Lab8/MiniRegisterFile/RegisterFile.v
module RegisterFile(BusA, BusB, BusW, RA, RB, RW, RegWr, Clk);
   output [63:0] BusA;
   output [63:0] BusB;
   input [63:0]  BusW;
   input [4:0] 	 RA;
   input [4:0] 	 RB;
   input [4:0] 	 RW;
   input 	 RegWr;
   input 	 Clk;
   
   reg [63:0] 	 register [31:0]; // 64, 32-bit registers
   
   
   always@(negedge Clk) begin
      
      if(RegWr)begin
	 if(RW != 31)begin
	    register[RW] <= BusW;
	 end
      end
      
   end
   assign BusA = (RA==31)?0:register[RA]; // RA indices the registers value on BusA
   assign BusB = (RB==31)?0:register[RB];// RB indices the registers value on BusB
endmodule

Lab8/RegisterFile/RegisterFile_Test.v
`timescale 1ns / 1ps
`define STRLEN 32
module RegisterFileTest_v;
   
   
   task passTest;
      input [63:0] actualOut, expectedOut;
      input [`STRLEN*8:0] testType;
      inout [7:0] 	  passed;
      
      if(actualOut == expectedOut) begin $display ("%s passed", testType); passed = passed + 1; end
      else $display ("%s failed: %d should be %d", testType, actualOut, expectedOut);
   endtask
   
   task allPassed;
      input [7:0] passed;
      input [7:0] numTests;
      
      if(passed == numTests) $display ("All tests passed");
      else $display("Some tests failed");
   endtask
   
   // Inputs
   reg [63:0] 	  BusW;
   reg [4:0] 	  RA;
   reg [4:0] 	  RB;
   reg [4:0] 	  RW;
   reg 		  RegWr;
   reg 		  Clk;
   reg [7:0] 	  passed;
   
   // Outputs
   wire [63:0] 	  BusA;
   wire [63:0] 	  BusB;
   
   // Instantiate the Unit Under Test (UUT)
   RegisterFile uut (
		     .BusA(BusA), 
		     .BusB(BusB), 
		     .BusW(BusW), 
		     .RA(RA), 
		     .RB(RB), 
		     .RW(RW), 
		     .RegWr(RegWr), 
		     .Clk(Clk)
		     );
   
   initial begin
      // Initialize Inputs
      BusW = 0;
      RA = 0;
      RB = 0;
      RW = 0;
      RegWr = 0;
      Clk = 1;
      passed = 0;
      
      {RA, RB, RW, BusW, RegWr} = {5'd0, 5'd0, 5'd0, 64'h0, 1'b1};#10; Clk = 0; #10; Clk = 1;
      {RA, RB, RW, BusW, RegWr} = {5'd0, 5'd0, 5'd1, 64'h1, 1'b1};#10; Clk = 0; #10; Clk = 1;
      {RA, RB, RW, BusW, RegWr} = {5'd0, 5'd0, 5'd2, 64'h2, 1'b1};#10; Clk = 0; #10; Clk = 1;
      {RA, RB, RW, BusW, RegWr} = {5'd0, 5'd0, 5'd3, 64'h3, 1'b1};#10; Clk = 0; #10; Clk = 1;
      {RA, RB, RW, BusW, RegWr} = {5'd0, 5'd0, 5'd4, 64'h4, 1'b1};#10; Clk = 0; #10; Clk = 1;
      {RA, RB, RW, BusW, RegWr} = {5'd0, 5'd0, 5'd5, 64'h5, 1'b1};#10; Clk = 0; #10; Clk = 1;
      {RA, RB, RW, BusW, RegWr} = {5'd0, 5'd0, 5'd6, 64'h6, 1'b1};#10; Clk = 0; #10; Clk = 1;
      {RA, RB, RW, BusW, RegWr} = {5'd0, 5'd0, 5'd7, 64'h7, 1'b1};#10; Clk = 0; #10; Clk = 1;
      {RA, RB, RW, BusW, RegWr} = {5'd0, 5'd0, 5'd8, 64'h8, 1'b1};#10; Clk = 0; #10; Clk = 1;
      {RA, RB, RW, BusW, RegWr} = {5'd0, 5'd0, 5'd9, 64'h9, 1'b1};#10; Clk = 0; #10; Clk = 1;
      {RA, RB, RW, BusW, RegWr} = {5'd0, 5'd0, 5'd10, 64'h10, 1'b1};#10; Clk = 0; #10; Clk = 1;
      {RA, RB, RW, BusW, RegWr} = {5'd0, 5'd0, 5'd11, 64'h11, 1'b1};#10; Clk = 0; #10; Clk = 1;
      {RA, RB, RW, BusW, RegWr} = {5'd0, 5'd0, 5'd12, 64'h12, 1'b1};#10; Clk = 0; #10; Clk = 1;
      {RA, RB, RW, BusW, RegWr} = {5'd0, 5'd0, 5'd13, 64'h13, 1'b1};#10; Clk = 0; #10; Clk = 1;
      {RA, RB, RW, BusW, RegWr} = {5'd0, 5'd0, 5'd14, 64'h14, 1'b1};#10; Clk = 0; #10; Clk = 1;
      {RA, RB, RW, BusW, RegWr} = {5'd0, 5'd0, 5'd15, 64'h15, 1'b1};#10; Clk = 0; #10; Clk = 1;
      {RA, RB, RW, BusW, RegWr} = {5'd0, 5'd0, 5'd16, 64'h16, 1'b1};#10; Clk = 0; #10; Clk = 1;
      {RA, RB, RW, BusW, RegWr} = {5'd0, 5'd0, 5'd17, 64'h17, 1'b1};#10; Clk = 0; #10; Clk = 1;
      {RA, RB, RW, BusW, RegWr} = {5'd0, 5'd0, 5'd18, 64'h18, 1'b1};#10; Clk = 0; #10; Clk = 1;
      {RA, RB, RW, BusW, RegWr} = {5'd0, 5'd0, 5'd19, 64'h19, 1'b1};#10; Clk = 0; #10; Clk = 1;
      {RA, RB, RW, BusW, RegWr} = {5'd0, 5'd0, 5'd20, 64'h20, 1'b1};#10; Clk = 0; #10; Clk = 1;
      {RA, RB, RW, BusW, RegWr} = {5'd0, 5'd0, 5'd21, 64'h21, 1'b1};#10; Clk = 0; #10; Clk = 1;
      {RA, RB, RW, BusW, RegWr} = {5'd0, 5'd0, 5'd22, 64'h22, 1'b1};#10; Clk = 0; #10; Clk = 1;
      {RA, RB, RW, BusW, RegWr} = {5'd0, 5'd0, 5'd23, 64'h23, 1'b1};#10; Clk = 0; #10; Clk = 1;
      {RA, RB, RW, BusW, RegWr} = {5'd0, 5'd0, 5'd24, 64'h24, 1'b1};#10; Clk = 0; #10; Clk = 1;
      {RA, RB, RW, BusW, RegWr} = {5'd0, 5'd0, 5'd25, 64'h25, 1'b1};#10; Clk = 0; #10; Clk = 1;
      {RA, RB, RW, BusW, RegWr} = {5'd0, 5'd0, 5'd26, 64'h26, 1'b1};#10; Clk = 0; #10; Clk = 1;
      {RA, RB, RW, BusW, RegWr} = {5'd0, 5'd0, 5'd27, 64'h27, 1'b1};#10; Clk = 0; #10; Clk = 1;
      {RA, RB, RW, BusW, RegWr} = {5'd0, 5'd0, 5'd28, 64'h28, 1'b1};#10; Clk = 0; #10; Clk = 1;
      {RA, RB, RW, BusW, RegWr} = {5'd0, 5'd0, 5'd29, 64'h29, 1'b1};#10; Clk = 0; #10; Clk = 1;
      {RA, RB, RW, BusW, RegWr} = {5'd0, 5'd0, 5'd30, 64'h30, 1'b1};#10; Clk = 0; #10; Clk = 1;
      {RA, RB, RW, BusW, RegWr} = {5'd0, 5'd0, 5'd31, 64'h31, 1'b1};#10; Clk = 0; #10; Clk = 1;
      
      
      //Adding custom test cases
      {RA, RB, RW, BusW, RegWr} = {5'd0, 5'd1, 5'd0, 64'h0, 1'b0};
      #4;
      passTest(BusA, 64'h0, "Check 1 Bus A", passed);
      passTest(BusB, 64'h1, "Check 1 Bus B", passed);
      #6; Clk = 0; #10; Clk = 1;
      {RA, RB, RW, BusW, RegWr} = {5'd2, 5'd3, 5'd1, 64'h1000, 1'b0};
      #4;
      passTest(BusA, 64'h2, "Check 2 Bus A", passed);
      passTest(BusB, 64'h3, "Check 2 Bus B", passed);
      #6; Clk = 0; #10; Clk = 1;
      {RA, RB, RW, BusW, RegWr} = {5'd4, 5'd5, 5'd0, 64'h1000, 1'b1};
      #4;
      passTest(BusA, 64'h4, "Check 3 Bus A", passed);
      passTest(BusB, 64'h5, "Check 3 Bus B", passed);
      #6; Clk = 0; #10; Clk = 1;
      {RA, RB, RW, BusW, RegWr} = {5'd6, 5'd7, 5'd10, 64'h1010, 1'b1};
      #4;
      passTest(BusA, 64'h6, "Check 4 Bus A", passed);
      passTest(BusB, 64'h7, "Check 4 Bus B", passed);
      #6; Clk = 0; #10; Clk = 1;
      {RA, RB, RW, BusW, RegWr} = {5'd8, 5'd9, 5'd11, 64'h103000, 1'b1};
      #4;
      passTest(BusA, 64'h8, "Check 5 Bus A", passed);
      passTest(BusB, 64'h9, "Check 5 Bus B", passed);
      #6; Clk = 0; #10; Clk = 1;
      {RA, RB, RW, BusW, RegWr} = {5'd10, 5'd11, 5'd12, 64'h0, 1'b0};
      #4;
      passTest(BusA, 64'd4112, "Check 6 Bus A", passed);
      passTest(BusB, 64'd1060864, "Check 6 Bus B", passed);
      #6; Clk = 0; #10; Clk = 1;
      {RA, RB, RW, BusW, RegWr} = {5'd12, 5'd13, 5'd13, 64'hABCD, 1'b1};
      #4;
      passTest(BusA, 64'd18, "Check 7 Bus A", passed);
      passTest(BusB, 64'd19, "Check 7 Bus B", passed);
      #6; Clk = 0; #10; Clk = 1;
      {RA, RB, RW, BusW, RegWr} = {5'd14, 5'd15, 5'd14, 64'h9080009, 1'b0};
      #4;
      passTest(BusA, 64'd20, "Check 8 Bus A", passed);
      passTest(BusB, 64'd21, "Check 8 Bus B", passed);
      #6; Clk = 0; #10; Clk = 1;
      
      allPassed(passed, 16);
   end
   initial begin
      $dumpfile("dump.vcd");
      $dumpvars(1);
   end
endmodule

Lab8/RegisterFile/dump.vcd
$date
	Tue Nov 10 22:52:26 2020
$end
$version
	Icarus Verilog
$end
$timescale
	1ps
$end
$scope module RegisterFileTest_v $end
$var wire 64 ! BusB [63:0] $end
$var wire 64 " BusA [63:0] $end
$var reg 64 # BusW [63:0] $end
$var reg 1 $ Clk $end
$var reg 5 % RA [4:0] $end
$var reg 5 & RB [4:0] $end
$var reg 5 ' RW [4:0] $end
$var reg 1 ( RegWr $end
$var reg 8 ) passed [7:0] $end
$upscope $end
$enddefinitions $end
#0
$dumpvars
b0 )
1(
b0 '
b0 &
b0 %
1$
b0 #
bx "
bx !
$end
#10000
b0 "
b0 !
0$
#20000
b1 '
b1 #
1$
#30000
0$
#40000
b10 '
b10 #
1$
#50000
0$
#60000
b11 '
b11 #
1$
#70000
0$
#80000
b100 '
b100 #
1$
#90000
0$
#100000
b101 '
b101 #
1$
#110000
0$
#120000
b110 '
b110 #
1$
#130000
0$
#140000
b111 '
b111 #
1$
#150000
0$
#160000
b1000 '
b1000 #
1$
#170000
0$
#180000
b1001 '
b1001 #
1$
#190000
0$
#200000
b1010 '
b10000 #
1$
#210000
0$
#220000
b1011 '
b10001 #
1$
#230000
0$
#240000
b1100 '
b10010 #
1$
#250000
0$
#260000
b1101 '
b10011 #
1$
#270000
0$
#280000
b1110 '
b10100 #
1$
#290000
0$
#300000
b1111 '
b10101 #
1$
#310000
0$
#320000
b10000 '
b10110 #
1$
#330000
0$
#340000
b10001 '
b10111 #
1$
#350000
0$
#360000
b10010 '
b11000 #
1$
#370000
0$
#380000
b10011 '
b11001 #
1$
#390000
0$
#400000
b10100 '
b100000 #
1$
#410000
0$
#420000
b10101 '
b100001 #
1$
#430000
0$
#440000
b10110 '
b100010 #
1$
#450000
0$
#460000
b10111 '
b100011 #
1$
#470000
0$
#480000
b11000 '
b100100 #
1$
#490000
0$
#500000
b11001 '
b100101 #
1$
#510000
0$
#520000
b11010 '
b100110 #
1$
#530000
0$
#540000
b11011 '
b100111 #
1$
#550000
0$
#560000
b11100 '
b101000 #
1$
#570000
0$
#580000
b11101 '
b101001 #
1$
#590000
0$
#600000
b11110 '
b110000 #
1$
#610000
0$
#620000
b11111 '
b110001 #
1$
#630000
0$
#640000
b1 !
b1 &
b0 '
b0 #
0(
1$
#644000
b10 )
#650000
0$
#660000
b10 "
b11 !
b10 %
b11 &
b1 '
b1000000000000 #
1$
#664000
b100 )
#670000
0$
#680000
b100 "
b101 !
b100 %
b101 &
b0 '
1(
1$
#684000
b110 )
#690000
0$
#700000
b110 "
b111 !
b110 %
b111 &
b1010 '
b1000000010000 #
1$
#704000
b1000 )
#710000
0$
#720000
b1000 "
b1001 !
b1000 %
b1001 &
b1011 '
b100000011000000000000 #
1$
#724000
b1010 )
#730000
0$
#740000
b1000000010000 "
b100000011000000000000 !
b1010 %
b1011 &
b1100 '
b0 #
0(
1$
#744000
b1100 )
#750000
0$
#760000
b10010 "
b10011 !
b1100 %
b1101 &
b1101 '
b1010101111001101 #
1(
1$
#764000
b1110 )
#770000
b1010101111001101 !
0$
#780000
b10100 "
b10101 !
b1110 %
b1111 &
b1110 '
b1001000010000000000000001001 #
0(
1$
#784000
b10000 )
