Lab9/Question 5/DataMemory.v
`timescale 1ns / 1ps

`define SIZE 1024

module DataMemory(ReadData , Address , WriteData , MemoryRead , MemoryWrite , Clock);
   input [63:0]      WriteData;
   input [63:0]      Address;
   input             Clock, MemoryRead, MemoryWrite;
   output reg [63:0] ReadData;

   reg [7:0] 	     memBank [`SIZE-1:0];


   // This task is used to write arbitrary data to the Data Memory by
   // the intialization block.
   task initset;
      input [63:0] addr;
      input [63:0] data;
      begin
	 memBank[addr] =  data[63:56] ; // Big-endian for the win...
	 memBank[addr+1] =  data[55:48];
	 memBank[addr+2] =  data[47:40];
	 memBank[addr+3] =  data[39:32];
	 memBank[addr+4] =  data[31:24];
	 memBank[addr+5] =  data[23:16];
	 memBank[addr+6] =  data[15:8];
	 memBank[addr+7] =  data[7:0];
      end
   endtask


   initial
     begin
        // preseting some data in the data memory used by test #1

        // Address 0x0 gets 0x1
        initset( 64'h0,  64'h1);  //Counter variable
        initset( 64'h8,  64'ha);  //Part of mask
        initset( 64'h10, 64'h5);  //Other part of mask
        initset( 64'h18, 64'h0ffbea7deadbeeff); //big constant
        initset( 64'h20, 64'h0); //clearing space

        // Add any data you need for your tests here.

     end

   // This always block reads the data memory and places a double word
   // on the ReadData bus.
   always @(posedge Clock)
     begin
        if(MemoryRead)
          begin
             ReadData[63:56] <= #20 memBank[Address];
             ReadData[55:48] <= #20 memBank[Address+1];
             ReadData[47:40] <= #20 memBank[Address+2];
             ReadData[39:32] <= #20 memBank[Address+3];
             ReadData[31:24] <= #20 memBank[Address+4];
             ReadData[23:16] <= #20 memBank[Address+5];
             ReadData[15:8] <= #20 memBank[Address+6];
             ReadData[7:0] <= #20 memBank[Address+7];
          end
     end

   // This always block takes data from the WriteData bus and writes
   // it into the DataMemory.
   always @(posedge Clock)
     begin
        if(MemoryWrite)
          begin
             memBank[Address] <= #20 WriteData[63:56] ;
             memBank[Address+1] <= #20 WriteData[55:48];
             memBank[Address+2] <= #20 WriteData[47:40];
             memBank[Address+3] <= #20 WriteData[39:32];
             memBank[Address+4] <= #20 WriteData[31:24];
             memBank[Address+5] <= #20 WriteData[23:16];
             memBank[Address+6] <= #20 WriteData[15:8];
             memBank[Address+7] <= #20 WriteData[7:0];
             // Could be useful for debugging:
             // $display("Writing Address:%h Data:%h",Address, WriteData);
          end
     end
endmodule

Lab9/Question 3/ALU.v
`define AND   4'b0000
`define OR    4'b0001
`define ADD   4'b0010
`define SUB   4'b0110
`define PassB 4'b0111

`timescale 1ns / 1ps

module ALU(BusW, BusA, BusB, ALUCtrl, Zero);
   
   parameter n = 64;

   output  [n-1:0] BusW;
   input [n-1:0]   BusA, BusB;
   input [3:0] 	   ALUCtrl;
   output 	   Zero;
   
   reg [n-1:0] 	   BusW;
   
   always @(ALUCtrl or BusA or BusB) begin
      case(ALUCtrl)
        `AND: BusW <= #20 BusA & BusB;
        `OR:  BusW <= #20 BusA | BusB;
        `ADD: BusW <= #20 BusA + BusB;
        `SUB: BusW <= #20 BusA - BusB;
        `PassB: BusW <= #20 BusB;
        default: BusW <= #20 0;
        
      endcase
   end

   assign #1 Zero = (BusW==64'b0) ? 1:0;
endmodule

Lab9/Question 5/SignExtender.v
`timescale 1ns/ 1ps
module SignExtender(BusImm, Imm26, Ctrl);

   input [25:0] Imm26;
   input [2:0] 	Ctrl;
   output reg [63:0] BusImm;

   always@(*) begin
      case(Ctrl)
        3'b001: BusImm = {{45{Imm26[23]}}, Imm26[23:5]}; // CBZ
        3'b011: BusImm = {{36{Imm26[25]}}, Imm26[25:0]}; // B
        3'b000: BusImm = {{55{Imm26[20]}}, Imm26[20:12]};  // D type instruction
        3'b010: BusImm = {52'b0, Imm26[21:10]}; // I type instruction
        3'b111: // IW type instruction
	   
	  begin
	     case(Imm26[22:21])
	       2'b00: BusImm <= {{48{1'b0}}, Imm26[20:5]};
	       2'b01: BusImm <= {{32{1'b0}}, {Imm26[20:5], {16{1'b0}}}};
	       2'b10: BusImm <= {{16{1'b0}}, {Imm26[20:5], {32{1'b0}}}};
	       2'b11: BusImm <= {Imm26[20:5], {48{1'b0}}};
	     endcase
	  end

	default: BusImm <= 64'b0;
      endcase
   end
endmodule

Lab9/Question 5/RegisterFile.v
`timescale 1ns/1ps
module RegisterFile(BusA, BusB, BusW, RW, RA, RB, RegWr, Clk);
   output [63:0] BusA;
   output [63:0] BusB;
   input [63:0]  BusW;
   input [4:0] 	 RA,RB,RW;
   input 	 RegWr;
   input 	 Clk;
   reg [63:0] 	 registers [31:0];

   integer 	 i;
   initial begin
      for(i=0; i<32; i++) begin
         registers[i] = 0;
      end
   end

   assign #2 BusA = registers[RA];
   assign #2 BusB = registers[RB];
   
   always @ (negedge Clk) begin
      if(RegWr && RW != 31)
        registers[RW] <= #3 BusW;
   end
endmodule

Lab9/Question 5/NextPClogic.v
`timescale 1ns / 1ps

module NextPClogic(NextPC, CurrentPC, SignExtImm64, Branch, ALUZero, Uncondbranch);
   input [63:0] CurrentPC, SignExtImm64;
   input 	Branch, ALUZero, Uncondbranch;
   output reg [63:0] NextPC;

   reg [63:0] 	     PC_4;

   always @(*) begin
      if(Uncondbranch|(Branch && ALUZero))
	NextPC <= #2 (SignExtImm64 << 2) + CurrentPC;
      else
	NextPC <= #1 CurrentPC + 4;
   end
endmodule

Lab9/Question 5/SingleCycleControl.v
`define OPCODE_ANDREG 11'b?0001010???
`define OPCODE_ORRREG 11'b?0101010???
`define OPCODE_ADDREG 11'b?0?01011???
`define OPCODE_SUBREG 11'b?1?01011???

`define OPCODE_ADDIMM 11'b?0?10001???
`define OPCODE_SUBIMM 11'b?1?10001???

`define OPCODE_MOVZ   11'b110100101??

`define OPCODE_B      11'b?00101?????
`define OPCODE_CBZ    11'b?011010????

`define OPCODE_LDUR   11'b??111000010
`define OPCODE_STUR   11'b??111000000

module control(
	       output reg 	reg2loc,
	       output reg 	alusrc,
	       output reg 	mem2reg,
	       output reg 	regwrite,
	       output reg 	memread,
	       output reg 	memwrite,
	       output reg 	branch,
	       output reg 	uncond_branch,
	       output reg [3:0] aluop,
	       output reg [2:0] signop, // added one bit to the output (I believe it will be needed)
	       input [10:0] 	opcode
	       );

   always @(*)
     begin
	casez (opcode)

          /* Add cases here for each instruction your processor supports */
	  // Values are from the last question in pre-lab 9

	  `OPCODE_LDUR: begin 
             reg2loc         <= #3 1'b0;
             alusrc          <= #3 1'b1;
             mem2reg         <= #3 1'b1;
             regwrite        <= #3 1'b1;
             memread         <= #3 1'b1;
             memwrite        <= #3 1'b0;
             branch          <= #3 1'b0;
             uncond_branch   <= #3 1'b0;
             aluop           <= 4'b0010; 
             signop          <= 3'b000; 
	  end

	  `OPCODE_STUR: begin 
             reg2loc         <= #3 1'b1;
             alusrc          <= #3 1'b1;
             mem2reg         <= #3 1'b0;
             regwrite        <= #3 1'b0;
             memread         <= #3 1'b0;
             memwrite        <= #3 1'b1;
             branch          <= #3 1'b0;
             uncond_branch   <= #3 1'b0;
             aluop           <= 4'b0010;
             signop          <= 3'b000;   
	  end
	  
	  `OPCODE_ADDREG: begin 
             reg2loc         <= #3 1'b0;
             alusrc          <= #3 1'b0;
             mem2reg         <= #3 1'b0;
             regwrite        <= #3 1'b1;
             memread         <= #3 1'b0;
             memwrite        <= #3 1'b0;
             branch          <= #3 1'b0;
             uncond_branch   <= #3 1'b0;
             aluop           <= 4'b0010;
             signop          <= 3'b000;
	  end
	  `OPCODE_SUBREG: begin 
             reg2loc         <= #3 1'b0;
             alusrc          <= #3 1'b0;
             mem2reg         <= #3 1'b0;
             regwrite        <= #3 1'b1;
             memread         <= #3 1'b0;
             memwrite        <= #3 1'b0;
             branch          <= #3 1'b0;
             uncond_branch   <= #3 1'b0;
             aluop           <= 4'b0110;
             signop          <= 3'b000;

          end
	  `OPCODE_ANDREG: begin 
             reg2loc         <= #3 1'b0;
             alusrc          <= #3 1'b0;
             mem2reg         <= #3 1'b0;
             regwrite        <= #3 1'b1;
             memread         <= #3 1'b0;
             memwrite        <= #3 1'b0;
             branch          <= #3 1'b0;
             uncond_branch   <= #3 1'b0;
             aluop           <= 4'b0000;
             signop          <= 3'b000;        
          end

	  `OPCODE_ORRREG: begin 
             reg2loc         <= #3 1'b0;
             alusrc          <= #3 1'b0;
             mem2reg         <= #3 1'b0;
             regwrite        <= #3 1'b1;
             memread         <= #3 1'b0;
             memwrite        <= #3 1'b0;
             branch          <= #3 1'b0;
             uncond_branch   <= #3 1'b0;
             aluop           <= 4'b0001;
             signop          <= 3'b000;
	  end
	  
	  `OPCODE_CBZ: begin 
             reg2loc         <= #3 1'b1;
             alusrc          <= #3 1'b0;
             mem2reg         <= #3 1'b0;
             regwrite        <= #3 1'b0;
             memread         <= #3 1'b0;
             memwrite        <= #3 1'b0;
             branch          <= #3 1'b1;
             uncond_branch   <= #3 1'b0;
             aluop           <= 4'b0111;
             signop          <= 3'b001;
	  end

	  `OPCODE_B: begin 
             reg2loc         <= #3 1'b0;
             alusrc          <= #3 1'b0;
             mem2reg         <= #3 1'b0;
             regwrite        <= #3 1'b0;
             memread         <= #3 1'b0;
             memwrite        <= #3 1'b0;
             branch          <= #3 1'b0;
             uncond_branch   <= #3 1'b1;
             aluop           <= 4'b0000;
             signop          <= 3'b011;        
	  end

	  `OPCODE_ADDIMM: begin 
             reg2loc         <= #3 1'b0;
             alusrc          <= #3 1'b1;
             mem2reg         <= #3 1'b0;
             regwrite        <= #3 1'b1;
             memread         <= #3 1'b0;
             memwrite        <= #3 1'b0;
             branch          <= #3 1'b0;
             uncond_branch   <= #3 1'b0;
             aluop           <= 4'b0010;
             signop          <= 3'b010;        
	  end

	  `OPCODE_SUBIMM: begin 
             reg2loc         <= #3 1'b0;
             alusrc          <= #3 1'b1;
             mem2reg         <= #3 1'b0;
             regwrite        <= #3 1'b1;
             memread         <= #3 1'b0;
             memwrite        <= #3 1'b0;
             branch          <= #3 1'b0;
             uncond_branch   <= #3 1'b0;
             aluop           <= 4'b0110;
             signop          <= 3'b010;        
	  end // case: `OPCODE_SUBIMM

	  // MOVZ Instruction Added:
	  `OPCODE_MOVZ: begin 
             reg2loc         <= #3 1'b0;
             alusrc          <= #3 1'b1;
             mem2reg         <= #3 1'b0;
             regwrite        <= #3 1'b1;
             memread         <= #3 1'b0;
             memwrite        <= #3 1'b0;
             branch          <= #3 1'b0;
             uncond_branch   <= #3 1'b0;
             aluop           <= 4'b0111;
             signop          <= 3'b111; 
	  end

	  default:
	    begin
               reg2loc       <= 1'b0;
               alusrc        <= 1'b0;
               mem2reg       <= 1'b0;
               regwrite      <= 1'b0;
               memread       <= 1'b0;
               memwrite      <= 1'b0;
               branch        <= 1'b0;
               uncond_branch <= 1'b0;
               aluop         <= 4'b0000;
               signop        <= 3'b000;
	    end
	endcase
     end

endmodule

Lab9/Question 5/InstructionMemory.v
`timescale 1ns / 1ps
/*
 * Module: InstructionMemory
 *
 * Implements read-only instruction memory
 * 
 */
module InstructionMemory(Data, Address);
   parameter T_rd = 20;
   parameter MemSize = 40;
   
   output [31:0] Data;
   input [63:0]  Address;
   reg [31:0] 	 Data;
   
   /*
    * ECEN 350 Processor Test Functions
    * Texas A&M University
    */
   
   always @ (Address) begin
      #4;
      case(Address)

	/* Test Program 1:
	 * Program loads constants from the data memory. Uses these constants to test
	 * the following instructions: LDUR, ORR, AND, CBZ, ADD, SUB, STUR and B.
	 * 
	 * Assembly code for test:
	 * 
	 * 0: LDUR X9, [XZR, 0x0]    //Load 1 into x9
	 * 4: LDUR X10, [XZR, 0x8]   //Load a into x10
	 * 8: LDUR X11, [XZR, 0x10]  //Load 5 into x11
	 * C: LDUR X12, [XZR, 0x18]  //Load big constant into x12
	 * 10: LDUR X13, [XZR, 0x20]  //load a 0 into X13
	 * 
	 * 14: ORR X10, X10, X11  //Create mask of 0xf
	 * 18: AND X12, X12, X10  //Mask off low order bits of big constant
	 * 
	 * loop:
	 * 1C: CBZ X12, end  //while X12 is not 0
	 * 20: ADD X13, X13, X9  //Increment counter in X13
	 * 24: SUB X12, X12, X9  //Decrement remainder of big constant in X12
	 * 28: B loop  //Repeat till X12 is 0
	 * 2C: STUR X13, [XZR, 0x20]  //store back the counter value into the memory location 0x20
	 */
	

	63'h000: Data = 32'hF84003E9;
	63'h004: Data = 32'hF84083EA;
	63'h008: Data = 32'hF84103EB;
	63'h00c: Data = 32'hF84183EC;
	63'h010: Data = 32'hF84203ED;
	63'h014: Data = 32'hAA0B014A;
	63'h018: Data = 32'h8A0A018C;
	63'h01c: Data = 32'hB400008C;
	63'h020: Data = 32'h8B0901AD;
	63'h024: Data = 32'hCB09018C;
	63'h028: Data = 32'h17FFFFFD;
	63'h02c: Data = 32'hF80203ED;
	63'h030: Data = 32'hF84203ED;  //One last load to place stored value on memdbus for test checking.

	/* Add code for your tests here */

	/*
	 1. Use the MOVZ instruction to construct constant 0x123456789abcdef0 in X9.
	 
	 MOVZ X9 0x1234 {LSL 0x3} 
	 MOVZ X9 0x5678 {LSL 0x2}
	 MOVZ X9 0x9abc {LSL 0x1}
	 MOVZ X9 0xdef0 {LSL 0x0}
	 // combine all at X9
	 ORR X9,X9,X10
	 ORR X9,X9,X11
	 ORR X9,X9,X12
	 
	 2. Store this immediate value to memory at memory address 0x28
	 
	 STUR X9[XZR,0x28]
	
	  3.Load this value back to register X10 
	 
	 LDUR X10,[XZR,0x28]
	 
	*/
	
	63'h034: Data = 32'hD2E24689;
	63'h038: Data = 32'hD2CACF0A;
	63'h03c: Data = 32'hD2B3578B;
	63'h040: Data = 32'hD29BDE0C;
	63'h044: Data = 32'hAA0A0129;
	63'h048: Data = 32'hAA0B0129;
	63'h04c: Data = 32'hAA0C0129;
	63'h050: Data = 32'hF801C009;
	63'h054: Data = 32'hF841C00A; 

	
	default: Data = 32'hXXXXXXXX;
      endcase
   end
endmodule

Lab9/Question 5/SingleCycleProc.v
`timescale 1ns / 1ps

module singlecycle(
		   input 	     resetl,
		   input [63:0]      startpc,
		   output reg [63:0] currentpc,
		   output [63:0]     dmemout,
		   input 	     CLK
		   );

   // Next PC connections
   wire [63:0] 			     nextpc;       // The next PC, to be updated on clock cycle

   // Instruction Memory connections
   wire [31:0] 			     instruction;  // The current instruction

   // Parts of instruction
   wire [4:0] 			     rd;            // The destination register
   wire [4:0] 			     rm;            // Operand 1
   wire [4:0] 			     rn;            // Operand 2
   wire [10:0] 			     opcode;

   // Control wires
   wire 			     reg2loc;
   wire 			     alusrc;
   wire 			     mem2reg;
   wire 			     regwrite;
   wire 			     memread;
   wire 			     memwrite;
   wire 			     branch;
   wire 			     uncond_branch;
   wire [3:0] 			     aluctrl;
   wire [2:0] 			     signop;    

   // Register file connections
   wire [63:0] 			     regoutA;     // Output A
   wire [63:0] 			     regoutB;     // Output B
   wire [63:0] 			     reginW;      // Input Write Data (added this)
   
   // ALU connections
   wire [63:0] 			     aluout;
   wire [63:0] 			     MuxALU;    // (added this for functionality)
   wire 			     zero;

   // Sign Extender connections
   wire [63:0] 			     extimm;

   // PC update logic
   always @(negedge CLK)
     begin
        if (resetl)
          currentpc <= nextpc;
        else
          currentpc <= startpc;
     end

   // Parts of instruction
   assign rd = instruction[4:0];
   assign rm = instruction[9:5];
   assign rn = reg2loc ? instruction[4:0] : instruction[20:16];
   assign opcode = instruction[31:21];

   InstructionMemory InstructionMemory(
				       .Data(instruction),
				       .Address(currentpc)
				       );

   control control(
		   .reg2loc(reg2loc),
		   .alusrc(alusrc),
		   .mem2reg(mem2reg),
		   .regwrite(regwrite),
		   .memread(memread),
		   .memwrite(memwrite),
		   .branch(branch),
		   .uncond_branch(uncond_branch),
		   .aluop(aluctrl),
		   .signop(signop),
		   .opcode(opcode)
		   );

   /*
    * Connect the remaining datapath elements below.
    * Do not forget any additional multiplexers that may be required.
    */
   
   
   // Next PC Logic
   NextPClogic  NextPClogic(nextpc, currentpc, extimm, branch, zero, uncond_branch);
   
   // Register File
   assign reginW = mem2reg ? dmemout : aluout;     // 2:1 MUX to Write Data
   RegisterFile RegisterFile(regoutA, regoutB, reginW, rd, rm,  rn, regwrite, CLK);
   
   // Sign Extender
   SignExtender SignExtender(extimm, instruction[25:0], signop);
   
   // ALU
   assign MuxALU = alusrc ? extimm : regoutB;
   ALU ALU(aluout, regoutA, MuxALU, aluctrl, zero);
   
   // Data Memory
   DataMemory DataMemory(dmemout, aluout, regoutB, memread, memwrite, CLK);


endmodule

Lab9/Question 5/SingleCycleProcTest.v
`timescale 1ns / 1ps

`define STRLEN 32
`define HalfClockPeriod 60
`define ClockPeriod `HalfClockPeriod * 2

module SingleCycleProcTest_v;

   initial
     begin
        $dumpfile("singlecycle.vcd");
        $dumpvars;
     end

   // These tasks are used to check if a given test has passed and
   // confirm that all tests passed.
   task passTest;
      input [63:0] actualOut, expectedOut;
      input [`STRLEN*8:0] testType;
      inout [7:0] 	  passed;

      if(actualOut == expectedOut) begin $display ("%s passed", testType); passed = passed + 1; end
      else $display ("%s failed: 0x%x should be 0x%x", testType, actualOut, expectedOut);
   endtask

   task allPassed;
      input [7:0] passed;
      input [7:0] numTests;

      if(passed == numTests) $display ("All tests passed");
      else $display("Some tests failed: %d of %d passed", passed, numTests);
   endtask

   // Inputs
   reg 		  CLK;
   reg 		  Reset_L;
   reg [63:0] 	  startPC;
   reg [7:0] 	  passed;
   reg [15:0] 	  watchdog;

   // Outputs
   wire [63:0] 	  dMemOut;
   wire [63:0] 	  currentPC;

   // Instantiate the Unit Under Test (UUT)
   singlecycle uut (
		    .CLK(CLK),
		    .resetl(Reset_L),
		    .startpc(startPC),
		    .currentpc(currentPC),
		    .dmemout(dMemOut)
		    );

   initial begin
      // Initialize Inputs
      Reset_L = 1;
      startPC = 0;
      passed = 0;

      // Initialize Watchdog timer
      watchdog = 0;

      // Wait for global reset
      #(1 * `ClockPeriod);

      // Program 1
      #1
        Reset_L = 0; startPC = 0;
      #(1 * `ClockPeriod);
      Reset_L = 1;

      // ***********************************************************
      // This while loop will continue cycling the processor until the
      // PC reaches the final instruction in the first test.  If the
      // program forms an infinite loop, never reaching the end, the
      // watchdog timer will kick in and kill simulation after 64K
      // cycles.
      // ***********************************************************

      while (currentPC < 64'h34)
        begin
           #(1 * `ClockPeriod);
           $display("CurrentPC:%h",currentPC);
        end
      #(1 * `ClockPeriod);	// One more cycle to load the pass code from the DataMemory.
      passTest(dMemOut, 64'hF, "Results of Program 1", passed);
     
      // ***********************************************************
      // Add your new tests here
      // ***********************************************************
     
      while (currentPC < 64'h58)
        begin
           #(1 * `ClockPeriod);
           $display("CurrentPC:%h",currentPC);
        end
      #(1 * `ClockPeriod);	// One more cycle to load the pass code from the DataMemory.
      passTest(dMemOut, 64'h123456789abcdef0, "Results of Program 2", passed);

      // Done
      allPassed(passed, 2);   // Be sure to change the one to match
      // the number of tests you add.
      $finish;
   end

   initial begin
      CLK = 0;
   end

   // The following is correct if clock starts at LOW level at StartTime //
   always begin
      #`HalfClockPeriod CLK = ~CLK;
      #`HalfClockPeriod CLK = ~CLK;
      watchdog = watchdog +1;
   end

   // Kill the simulation if the watchdog hits 64K cycles
   always @*
     if (watchdog == 16'hFF)
       begin
          $display("Watchdog Timer Expired.");
          $finish;
       end


endmodule

Lab9/Question 5/singlecycle.vcd
$date
	Mon Nov 30 21:47:34 2020
$end
$version
	Icarus Verilog
$end
$timescale
	1ps
$end
$scope module SingleCycleProcTest_v $end
$var wire 64 ! dMemOut [63:0] $end
$var wire 64 " currentPC [63:0] $end
$var reg 1 # CLK $end
$var reg 1 $ Reset_L $end
$var reg 8 % passed [7:0] $end
$var reg 64 & startPC [63:0] $end
$var reg 16 ' watchdog [15:0] $end
$scope module uut $end
$var wire 1 # CLK $end
$var wire 1 $ resetl $end
$var wire 64 ( startpc [63:0] $end
$var wire 1 ) zero $end
$var wire 1 * uncond_branch $end
$var wire 3 + signop [2:0] $end
$var wire 5 , rn [4:0] $end
$var wire 5 - rm [4:0] $end
$var wire 1 . regwrite $end
$var wire 64 / regoutB [63:0] $end
$var wire 64 0 regoutA [63:0] $end
$var wire 64 1 reginW [63:0] $end
$var wire 1 2 reg2loc $end
$var wire 5 3 rd [4:0] $end
$var wire 11 4 opcode [10:0] $end
$var wire 64 5 nextpc [63:0] $end
$var wire 1 6 memwrite $end
$var wire 1 7 memread $end
$var wire 1 8 mem2reg $end
$var wire 32 9 instruction [31:0] $end
$var wire 64 : extimm [63:0] $end
$var wire 64 ; dmemout [63:0] $end
$var wire 1 < branch $end
$var wire 1 = alusrc $end
$var wire 64 > aluout [63:0] $end
$var wire 4 ? aluctrl [3:0] $end
$var wire 64 @ MuxALU [63:0] $end
$var reg 64 A currentpc [63:0] $end
$scope module ALU $end
$var wire 64 B BusB [63:0] $end
$var wire 1 ) Zero $end
$var wire 64 C BusA [63:0] $end
$var wire 4 D ALUCtrl [3:0] $end
$var reg 64 E BusW [63:0] $end
$upscope $end
$scope module DataMemory $end
$var wire 64 F Address [63:0] $end
$var wire 1 # Clock $end
$var wire 64 G WriteData [63:0] $end
$var wire 1 6 MemoryWrite $end
$var wire 1 7 MemoryRead $end
$var reg 64 H ReadData [63:0] $end
$scope task initset $end
$var reg 64 I addr [63:0] $end
$var reg 64 J data [63:0] $end
$upscope $end
$upscope $end
$scope module InstructionMemory $end
$var wire 64 K Address [63:0] $end
$var reg 32 L Data [31:0] $end
$upscope $end
$scope module NextPClogic $end
$var wire 1 ) ALUZero $end
$var wire 64 M CurrentPC [63:0] $end
$var wire 1 * Uncondbranch $end
$var wire 64 N SignExtImm64 [63:0] $end
$var wire 1 < Branch $end
$var reg 64 O NextPC [63:0] $end
$upscope $end
$scope module RegisterFile $end
$var wire 64 P BusA [63:0] $end
$var wire 64 Q BusB [63:0] $end
$var wire 64 R BusW [63:0] $end
$var wire 1 # Clk $end
$var wire 5 S RA [4:0] $end
$var wire 5 T RB [4:0] $end
$var wire 5 U RW [4:0] $end
$var wire 1 . RegWr $end
$var integer 32 V i [31:0] $end
$upscope $end
$scope module SignExtender $end
$var wire 26 W Imm26 [25:0] $end
$var wire 3 X Ctrl [2:0] $end
$var reg 64 Y BusImm [63:0] $end
$upscope $end
$scope module control $end
$var wire 11 Z opcode [10:0] $end
$var reg 4 [ aluop [3:0] $end
$var reg 1 = alusrc $end
$var reg 1 < branch $end
$var reg 1 8 mem2reg $end
$var reg 1 7 memread $end
$var reg 1 6 memwrite $end
$var reg 1 2 reg2loc $end
$var reg 1 . regwrite $end
$var reg 3 \ signop [2:0] $end
$var reg 1 * uncond_branch $end
$upscope $end
$upscope $end
$scope task allPassed $end
$var reg 8 ] numTests [7:0] $end
$var reg 8 ^ passed [7:0] $end
$upscope $end
$scope task passTest $end
$var reg 64 _ actualOut [63:0] $end
$var reg 64 ` expectedOut [63:0] $end
$var reg 8 a passed [7:0] $end
$var reg 257 b testType [256:0] $end
$upscope $end
$upscope $end
$enddefinitions $end
#0
$dumpvars
bx b
bx a
bx `
bx _
bx ^
bx ]
bx \
bx [
bx Z
bx Y
bx X
bx W
b100000 V
bx U
bx T
bx S
bx R
bx Q
bx P
bx O
bx N
bx M
bx L
bx K
b0 J
b100000 I
bx H
bx G
bx F
bx E
bx D
bx C
bx B
bx A
bx @
bx ?
bx >
x=
x<
bx ;
bx :
bx 9
x8
x7
x6
bx 5
bx 4
bx 3
x2
bx 1
bx 0
bx /
x.
bx -
bx ,
bx +
x*
x)
b0 (
b0 '
b0 &
b0 %
1$
0#
bx "
bx !
$end
#60000
1#
#120000
b1 '
0#
#121000
0$
#180000
1#
#240000
b0 "
b0 A
b0 K
b0 M
b10 '
0#
#241000
b100 5
b100 O
1$
#244000
b0 :
b0 N
b0 Y
b0 +
b0 X
b0 \
b10 ?
b10 D
b10 [
b0x00x ,
b0x00x T
b10000000000001111101001 W
b11111000010 4
b11111000010 Z
b11111 -
b11111 S
b1001 3
b1001 U
b11111000010000000000001111101001 9
b11111000010000000000001111101001 L
#246000
b0 0
b0 C
b0 P
#247000
b0 @
b0 B
b0 ,
b0 T
0*
0<
06
17
1.
18
1=
02
#249000
b0 /
b0 G
b0 Q
#267000
b0 >
b0 E
b0 F
#268000
1)
#300000
1#
#320000
b1 1
b1 R
b1 !
b1 ;
b1 H
#360000
b100 "
b100 A
b100 K
b100 M
b11 '
0#
#361000
b1000 5
b1000 O
#364000
b1000 @
b1000 B
b1000 :
b1000 N
b1000 Y
b10000001000001111101010 W
b1010 3
b1010 U
b11111000010000001000001111101010 9
b11111000010000001000001111101010 L
#384000
b1000 >
b1000 E
b1000 F
#385000
0)
#420000
1#
#440000
b1010 1
b1010 R
b1010 !
b1010 ;
b1010 H
#480000
b1000 "
b1000 A
b1000 K
b1000 M
b100 '
0#
#481000
b1100 5
b1100 O
#484000
b10000 @
b10000 B
b10000 :
b10000 N
b10000 Y
b1 ,
b1 T
b10000010000001111101011 W
b1011 3
b1011 U
b11111000010000010000001111101011 9
b11111000010000010000001111101011 L
#504000
b10000 >
b10000 E
b10000 F
#540000
1#
#560000
b101 1
b101 R
b101 !
b101 ;
b101 H
#600000
b1100 "
b1100 A
b1100 K
b1100 M
b101 '
0#
#601000
b10000 5
b10000 O
#604000
b11000 @
b11000 B
b11000 :
b11000 N
b11000 Y
b10000011000001111101100 W
b1100 3
b1100 U
b11111000010000011000001111101100 9
b11111000010000011000001111101100 L
#624000
b11000 >
b11000 E
b11000 F
#660000
1#
#680000
b111111111011111010100111110111101010110110111110111011111111 1
b111111111011111010100111110111101010110110111110111011111111 R
b111111111011111010100111110111101010110110111110111011111111 !
b111111111011111010100111110111101010110110111110111011111111 ;
b111111111011111010100111110111101010110110111110111011111111 H
#720000
b10000 "
b10000 A
b10000 K
b10000 M
b110 '
0#
#721000
b10100 5
b10100 O
#724000
b100000 @
b100000 B
b100000 :
b100000 N
b100000 Y
b10 ,
b10 T
b10000100000001111101101 W
b1101 3
b1101 U
b11111000010000100000001111101101 9
b11111000010000100000001111101101 L
#744000
b100000 >
b100000 E
b100000 F
#780000
1#
#800000
b0 1
b0 R
b0 !
b0 ;
b0 H
#840000
b10100 "
b10100 A
b10100 K
b10100 M
b111 '
0#
#841000
b11000 5
b11000 O
#844000
b1 ?
b1 D
b1 [
b10110000 @
b10110000 B
b10110000 :
b10110000 N
b10110000 Y
b1011 ,
b1011 T
b10000010110000000101001010 W
b10101010000 4
b10101010000 Z
b1010 -
b1010 S
b1010 3
b1010 U
b10101010000010110000000101001010 9
b10101010000010110000000101001010 L
#846000
b101 /
b101 G
b101 Q
b1010 0
b1010 C
b1010 P
#847000
b100000 1
b100000 R
b101 @
b101 B
07
08
0=
#864000
b10110000 1
b10110000 R
b10110000 >
b10110000 E
b10110000 F
#866000
b10111010 1
b10111010 R
b10111010 >
b10111010 E
b10111010 F
#867000
b1111 1
b1111 R
b1111 >
b1111 E
b1111 F
#900000
1#
#960000
b11000 "
b11000 A
b11000 K
b11000 M
b1000 '
0#
#961000
b11100 5
b11100 O
#964000
b0 ?
b0 D
b0 [
b10100000 :
b10100000 N
b10100000 Y
b1010 ,
b1010 T
b10000010100000000110001100 W
b10001010000 4
b10001010000 Z
b1100 -
b1100 S
b1100 3
b1100 U
b10001010000010100000000110001100 9
b10001010000010100000000110001100 L
#966000
b1111 @
b1111 B
b1111 /
b1111 G
b1111 Q
b111111111011111010100111110111101010110110111110111011111111 0
b111111111011111010100111110111101010110110111110111011111111 C
b111111111011111010100111110111101010110110111110111011111111 P
#984000
b0 1
b0 R
b0 >
b0 E
b0 F
#985000
1)
#986000
b1111 1
b1111 R
b1111 >
b1111 E
b1111 F
#987000
0)
#1020000
1#
#1080000
b11100 "
b11100 A
b11100 K
b11100 M
b1001 '
0#
#1081000
b100000 5
b100000 O
#1084000
b1 +
b1 X
b1 \
b111 ?
b111 D
b111 [
b100 :
b100 N
b100 Y
b0 ,
b0 T
b10001100 W
b10110100000 4
b10110100000 Z
b100 -
b100 S
b10110100000000000000000010001100 9
b10110100000000000000000010001100 L
#1086000
b0 @
b0 B
b0 /
b0 G
b0 Q
b0 0
b0 C
b0 P
#1087000
b1100 ,
b1100 T
1<
0.
12
#1089000
b1111 @
b1111 B
b1111 /
b1111 G
b1111 Q
#1106000
b0 1
b0 R
b0 >
b0 E
b0 F
#1107000
1)
#1109000
b1111 1
b1111 R
b101100 5
b101100 O
b1111 >
b1111 E
b1111 F
#1110000
0)
#1111000
b100000 5
b100000 O
#1140000
1#
#1200000
b100000 "
b100000 A
b100000 K
b100000 M
b1010 '
0#
#1201000
b100100 5
b100100 O
#1204000
b0 +
b0 X
b0 \
b10 ?
b10 D
b10 [
b10010000 :
b10010000 N
b10010000 Y
b1101 ,
b1101 T
b11000010010000000110101101 W
b10001011000 4
b10001011000 Z
b1101 -
b1101 S
b1101 3
b1101 U
b10001011000010010000000110101101 9
b10001011000010010000000110101101 L
#1206000
b0 @
b0 B
b0 /
b0 G
b0 Q
#1207000
b1001 ,
b1001 T
0<
1.
02
#1209000
b1 @
b1 B
b1 /
b1 G
b1 Q
#1226000
b0 1
b0 R
b0 >
b0 E
b0 F
#1227000
1)
#1229000
b1 1
b1 R
b1 >
b1 E
b1 F
#1230000
0)
#1260000
1#
#1320000
b100100 "
b100100 A
b100100 K
b100100 M
b1011 '
0#
#1321000
b101000 5
b101000 O
#1324000
b110 ?
b110 D
b110 [
b11000010010000000110001100 W
b11001011000 4
b11001011000 Z
b1100 -
b1100 S
b1100 3
b1100 U
b11001011000010010000000110001100 9
b11001011000010010000000110001100 L
#1326000
b1111 0
b1111 C
b1111 P
