Lab6/Lab/HalfAdder/Code/HalfAdd.v
module HalfAdd (Cout, Sum, A, B);
//This module describes a Half Adder using structural logic

input A, B; //declare inputs A and B
output Cout, Sum; //declare outputs Cout and Sum

//Internal Wires
wire W1, W2, W3; // we use 3 internal wires to get the desired output

//Gate-level modules, they define the operations performed for each wire
nand (W1, A, B); // wire 1 will hold the result from performing NAND with inputs A and B (NOT AND)
nand (W2, A, W1); // wire 2 will hold the result from performing NAND on input A and wire 1
nand (W3, W1, B); // wire 3 will hold the result from performing NAND on wires 1 and input B
nand (Sum, W2, W3); //Sum is nand of results from internal W2 and W3
nand (Cout, W1, W1); //Cout is nand of W1 and W1 for optimal designing

endmodule //designates the end of the module

Lab6/Lab/HalfAdder/Code/HalfAddTest.v
`timescale 1ns / 1ps

////////////////////////////////////////////////////////////////////////////////
// Company: 
// Engineer:
//
// Create Date:   15:12:10 03/02/2009
// Design Name:   HalfAdd
// Module Name:   E:/350/Lab6/HalfAdd/HalfAddTest.v
// Project Name:  HalfAdd
// Target Device:  
// Tool versions:  
// Description: 
//
// Verilog Test Fixture created by ISE for module: HalfAdd
//
// Dependencies:
// 
// Revision:
// Revision 0.01 - File Created
// Additional Comments:
// 
////////////////////////////////////////////////////////////////////////////////

`define STRLEN 15

module HalfAddTest_v;

   initial begin
      $dumpfile("HalfAddTest.vcd"); 
      $dumpvars(0, HalfAddTest_v);
   end
   
   
   task passTest;
      input [1:0] actualOut, expectedOut;
      input [`STRLEN*8:0] testType;
      inout [7:0]         passed;
      
      if(actualOut == expectedOut) begin $display ("%s passed", testType); passed = passed + 1; end
      else $display ("%s failed: %d should be %d", testType, actualOut, expectedOut);
   endtask
   
   task allPassed;
      input [7:0] passed;
      input [7:0] numTests;
      
      if(passed == numTests) $display ("All tests passed");
      else $display("Some tests failed");
   endtask

   // Inputs
   reg            A;
   reg            B;
   reg [7:0]      passed;

   // Outputs
   wire           Cout;
   wire           Sum;

   // Instantiate the Device Under Test (DUT)
   HalfAdd dut (
		.Cout(Cout), 
		.Sum(Sum), 
		.A(A), 
		.B(B)
	        );

   initial begin
      // Initialize Inputs
      A = 0;
      B = 0;
      passed = 0;

      // Add stimulus here
      #90; A=0;B=0; #10; passTest({Cout, Sum}, 0, "0+0", passed);
      #90; A=0;B=1; #10; passTest({Cout, Sum}, 1, "0+1", passed);
      #90; A=1;B=0; #10; passTest({Cout, Sum}, 1, "1+0", passed);
      #90; A=1;B=1; #10; passTest({Cout, Sum}, 2, "1+1", passed);
	  #90;
      
      allPassed(passed, 4);

   end
   
endmodule

Lab6/Lab/HalfAdder/Code/HalfAddTest.vcd
$date
	Wed Oct 14 07:35:17 2020
$end
$version
	Icarus Verilog
$end
$timescale
	1ps
$end
$scope module HalfAddTest_v $end
$var wire 1 ! Sum $end
$var wire 1 " Cout $end
$var reg 1 # A $end
$var reg 1 $ B $end
$var reg 8 % passed [7:0] $end
$scope module dut $end
$var wire 1 # A $end
$var wire 1 $ B $end
$var wire 1 " Cout $end
$var wire 1 ! Sum $end
$var wire 1 & W1 $end
$var wire 1 ' W2 $end
$var wire 1 ( W3 $end
$upscope $end
$scope task allPassed $end
$var reg 8 ) numTests [7:0] $end
$var reg 8 * passed [7:0] $end
$upscope $end
$scope task passTest $end
$var reg 2 + actualOut [1:0] $end
$var reg 2 , expectedOut [1:0] $end
$var reg 8 - passed [7:0] $end
$var reg 121 . testType [120:0] $end
$upscope $end
$upscope $end
$enddefinitions $end
#0
$dumpvars
bx .
bx -
bx ,
bx +
bx *
bx )
1(
1'
1&
b0 %
0$
0#
0"
0!
$end
#100000
b1 %
b1 -
b1100000010101100110000 .
b0 ,
b0 +
#190000
1!
0(
1$
#200000
b10 %
b10 -
b1100000010101100110001 .
b1 ,
b1 +
#290000
1(
0'
0$
1#
#300000
b11 %
b11 -
b1100010010101100110000 .
#390000
0!
1'
1"
0&
1(
1$
#400000
b100 %
b100 -
b1100010010101100110001 .
b10 ,
b10 +
#490000
b100 )
b100 *
